vbones/__init__.py
vbones/_version.py
vbones/hello.py
vbones-0.1.4.dist-info/licenses/LICENSE
vbones-0.1.4.dist-info/METADATA
vbones-0.1.4.dist-info/WHEEL
vbones-0.1.4.dist-info/top_level.txt
vbones-0.1.4.dist-info/RECORD
